README.rst
setup.cfg
setup.py
Gwydion.egg-info/PKG-INFO
Gwydion.egg-info/SOURCES.txt
Gwydion.egg-info/dependency_links.txt
Gwydion.egg-info/top_level.txt
gwydion/__init__.py
gwydion/base.py
gwydion/exceptions.py
gwydion/random_array.py
gwydion.egg-info/SOURCES.txt
gwydion/funcs/__init__.py
gwydion/funcs/exponential.py
gwydion/funcs/linear.py
gwydion/funcs/logarithm.py
gwydion/funcs/polynomial.py
gwydion/funcs/sine.py
gwydion/stats/__init__.py
gwydion/stats/normal.py