Metadata-Version: 1.1
Name: gwydion
Version: 0.1
Summary: Gwydion allows users to generate pseudo-random scientific data easily.
Home-page: https://github.com/Ffisegydd/Gwydion
Author: Keiron J. Pizzey
Author-email: kjpizzey@gmail.com
License: MIT
Platform: UNKNOWN
Classifier: Development Status :: 3 - Alpha
Classifier: Operating System :: OS Independent
Classifier: Intended Audience :: Developers
Classifier: Intended Audience :: Education
Classifier: Intended Audience :: Science/Research
Classifier: License :: OSI Approved :: MIT License
Classifier: Natural Language :: English
Classifier: Programming Language :: Python
Classifier: Programming Language :: Python :: 3
Classifier: Programming Language :: Python :: Implementation :: CPython
Classifier: Topic :: Scientific/Engineering
